flask_celery.py
Flask_Celery_py3-0.1.4.dist-info/DESCRIPTION.rst
Flask_Celery_py3-0.1.4.dist-info/METADATA
Flask_Celery_py3-0.1.4.dist-info/RECORD
Flask_Celery_py3-0.1.4.dist-info/WHEEL
Flask_Celery_py3-0.1.4.dist-info/metadata.json
Flask_Celery_py3-0.1.4.dist-info/top_level.txt
