Metadata-Version: 2.0
Name: Flask-Celery-py3
Version: 0.1.4
Summary: Celery 3.0+ integration for Flask (Python 3 version)
Home-page: https://github.com/taogeT/flask-celery
Author: Zheng Wentao
Author-email: zwtzjd@gmail.com
License: MIT
Platform: any
Classifier: Development Status :: 3 - Alpha
Classifier: Environment :: Web Environment
Classifier: Framework :: Flask
Classifier: Intended Audience :: Developers
Classifier: License :: OSI Approved :: MIT License
Classifier: Operating System :: OS Independent
Classifier: Programming Language :: Python
Classifier: Programming Language :: Python :: 3
Classifier: Programming Language :: Python :: 3.4
Classifier: Programming Language :: Python :: 3.5
Classifier: Topic :: Internet :: WWW/HTTP :: Dynamic Content
Classifier: Topic :: Software Development :: Libraries :: Python Modules
Requires-Dist: Celery (>=3.0.0)
Requires-Dist: Flask (>=0.9)
